timescape/__init__.py
timescape-1.0.1.dist-info/METADATA
timescape-1.0.1.dist-info/WHEEL
timescape-1.0.1.dist-info/top_level.txt
timescape-1.0.1.dist-info/RECORD
