Metadata-Version: 2.4
Name: timescape
Version: 1.0.1
Summary: Placeholder for the timescape name
